{
  "magic": "E!vIA5L86J2I",
  "timestamp": "2025-01-12T01:17:14.253988+00:00",
  "repo": "mirjak/draft-masque-mediabitrate",
  "labels": [
    {
      "name": "bug",
      "description": "Something isn't working",
      "color": "d73a4a"
    },
    {
      "name": "documentation",
      "description": "Improvements or additions to documentation",
      "color": "0075ca"
    },
    {
      "name": "duplicate",
      "description": "This issue or pull request already exists",
      "color": "cfd3d7"
    },
    {
      "name": "enhancement",
      "description": "New feature or request",
      "color": "a2eeef"
    },
    {
      "name": "good first issue",
      "description": "Good for newcomers",
      "color": "7057ff"
    },
    {
      "name": "help wanted",
      "description": "Extra attention is needed",
      "color": "008672"
    },
    {
      "name": "invalid",
      "description": "This doesn't seem right",
      "color": "e4e669"
    },
    {
      "name": "question",
      "description": "Further information is requested",
      "color": "d876e3"
    },
    {
      "name": "wontfix",
      "description": "This will not be worked on",
      "color": "ffffff"
    }
  ],
  "issues": [
    {
      "number": 1,
      "id": "I_kwDOLJj2Nc6ayqt-",
      "title": "Add applicability limited to existing masque proxies",
      "url": "https://github.com/mirjak/draft-masque-mediabitrate/issues/1",
      "state": "OPEN",
      "author": "mirjak",
      "authorAssociation": "OWNER",
      "assignees": [],
      "labels": [],
      "body": "Add a section that makes clear that this proposal does not consider discovery as it is assumed that there is already a masque proxy in place.",
      "createdAt": "2024-10-18T09:26:36Z",
      "updatedAt": "2024-10-21T18:17:20Z",
      "closedAt": null,
      "comments": [
        {
          "author": "ihlar",
          "authorAssociation": "COLLABORATOR",
          "body": "addressed in #2 ",
          "createdAt": "2024-10-21T18:17:18Z",
          "updatedAt": "2024-10-21T18:17:18Z"
        }
      ]
    }
  ],
  "pulls": [
    {
      "number": 2,
      "id": "PR_kwDOLJj2Nc5_W-BJ",
      "title": "Applicability",
      "url": "https://github.com/mirjak/draft-masque-mediabitrate/pull/2",
      "state": "MERGED",
      "author": "ihlar",
      "authorAssociation": "COLLABORATOR",
      "assignees": [],
      "labels": [],
      "body": "",
      "createdAt": "2024-10-21T18:11:34Z",
      "updatedAt": "2024-10-21T18:19:14Z",
      "baseRepository": "mirjak/draft-masque-mediabitrate",
      "baseRefName": "main",
      "baseRefOid": "e8f010d364130870ff4b13b5f099927efd50bebf",
      "headRepository": "mirjak/draft-masque-mediabitrate",
      "headRefName": "applicability",
      "headRefOid": "19fdf642a10bbc07a0d6d0df44b6343bb98dcb0f",
      "closedAt": "2024-10-21T18:19:14Z",
      "mergedAt": "2024-10-21T18:19:14Z",
      "mergedBy": "ihlar",
      "mergeCommit": {
        "oid": "199e4ce6331e6f82f6cafe5b4ee3872c9adaad67"
      },
      "comments": [],
      "reviews": []
    }
  ]
}